coco/__init__.py
coco/__main__.py
coco/coco.py
coco/consts.py
coco/eval.py
coco/log_utils.py
coco/main.py
coco/test_coco.py
coco/utils.py
cocotools-0.2.0.1.dist-info/METADATA
cocotools-0.2.0.1.dist-info/WHEEL
cocotools-0.2.0.1.dist-info/entry_points.txt
cocotools-0.2.0.1.dist-info/top_level.txt
cocotools-0.2.0.1.dist-info/RECORD
